JiandanMingxiangshu/Dockerfile
JiandanMingxiangshu/README.md
JiandanMingxiangshu/__init__.py
JiandanMingxiangshu/__main__.py
JiandanMingxiangshu/file.epub
JiandanMingxiangshu/index.html
JiandanMingxiangshu/css/__init__.py
JiandanMingxiangshu/css/annotations.css
JiandanMingxiangshu/css/main.css
JiandanMingxiangshu/css/normalize.css
JiandanMingxiangshu/css/popup.css
JiandanMingxiangshu/font/__init__.py
JiandanMingxiangshu/font/fontello.eot
JiandanMingxiangshu/font/fontello.svg
JiandanMingxiangshu/font/fontello.ttf
JiandanMingxiangshu/font/fontello.woff
JiandanMingxiangshu/img/__init__.py
JiandanMingxiangshu/img/annotator-glyph-sprite.png
JiandanMingxiangshu/img/annotator-icon-sprite.png
JiandanMingxiangshu/img/apple-touch-icon.png
JiandanMingxiangshu/img/cancelfullscreen.png
JiandanMingxiangshu/img/close.png
JiandanMingxiangshu/img/fullscreen.png
JiandanMingxiangshu/img/loader.gif
JiandanMingxiangshu/img/menu-icon.png
JiandanMingxiangshu/img/save.png
JiandanMingxiangshu/img/saved.png
JiandanMingxiangshu/img/settings-s.png
JiandanMingxiangshu/img/settings.png
JiandanMingxiangshu/img/star.png
JiandanMingxiangshu/js/__init__.py
JiandanMingxiangshu/js/epub.js
JiandanMingxiangshu/js/epub.min.js
JiandanMingxiangshu/js/epub.min.map
JiandanMingxiangshu/js/hooks.min.js
JiandanMingxiangshu/js/hooks.min.map
JiandanMingxiangshu/js/reader.js
JiandanMingxiangshu/js/reader.js.map
JiandanMingxiangshu/js/reader.min.js
JiandanMingxiangshu/js/reader.min.map
JiandanMingxiangshu/js/hooks/__init__.py
JiandanMingxiangshu/js/hooks/extensions/__init__.py
JiandanMingxiangshu/js/hooks/extensions/highlight.js
JiandanMingxiangshu/js/libs/__init__.py
JiandanMingxiangshu/js/libs/jquery.min.js
JiandanMingxiangshu/js/libs/localforage.min.js
JiandanMingxiangshu/js/libs/screenfull.js
JiandanMingxiangshu/js/libs/screenfull.min.js
JiandanMingxiangshu/js/libs/zip.min.js
JiandanMingxiangshu/js/plugins/__init__.py
JiandanMingxiangshu/js/plugins/hypothesis.js
JiandanMingxiangshu/js/plugins/search.js
jiandan_mingxiangshu-2022.10.9.1.dist-info/METADATA
jiandan_mingxiangshu-2022.10.9.1.dist-info/WHEEL
jiandan_mingxiangshu-2022.10.9.1.dist-info/entry_points.txt
jiandan_mingxiangshu-2022.10.9.1.dist-info/top_level.txt
jiandan_mingxiangshu-2022.10.9.1.dist-info/RECORD
